py_and_id/__init__.py
py_and_id/py_and_id.py
py_and_id/segments.py
py_and_id/settings.py
py_and_id/transform.py
py_and_id/types.py
py_and_id/util.py
py_and_id/backends/__init__.py
py_and_id/backends/mpl.py
py_and_id/backends/svg.py
py_and_id/backends/svgtext.py
py_and_id/dsp/__init__.py
py_and_id/dsp/dsp.py
py_and_id/dsp/legacy.py
py_and_id/elements/__init__.py
py_and_id/elements/compound.py
py_and_id/elements/connectors.py
py_and_id/elements/elements.py
py_and_id/elements/intcircuits.py
py_and_id/elements/legacy.py
py_and_id/elements/lines.py
py_and_id/elements/misc.py
py_and_id/elements/oneterm.py
py_and_id/elements/opamp.py
py_and_id/elements/outlets.py
py_and_id/elements/pipes.py
py_and_id/elements/rotary.py
py_and_id/elements/switches.py
py_and_id/elements/transistors.py
py_and_id/elements/twoterm.py
py_and_id/elements/xform.py
py_and_id/flow/__init__.py
py_and_id/flow/flow.py
py_and_id/flow/legacy.py
py_and_id/logic/__init__.py
py_and_id/logic/kmap.py
py_and_id/logic/legacy.py
py_and_id/logic/logic.py
py_and_id/logic/table.py
py_and_id/logic/timing.py
py_and_id/logic/timingwaves.py
py_and_id/parsing/__init__.py
py_and_id/parsing/buchheim.py
py_and_id/parsing/logic_parser.py
py_and_id-0.0.3.dist-info/LICENSE
py_and_id-0.0.3.dist-info/METADATA
py_and_id-0.0.3.dist-info/WHEEL
py_and_id-0.0.3.dist-info/top_level.txt
py_and_id-0.0.3.dist-info/RECORD
